virpipe/__init__.py
virpipe/__main__.py
virpipe/arguments/__init__.py
virpipe/arguments/parser.py
virpipe/arguments/validation.py
virpipe/command/__init__.py
virpipe/command/nextflow.py
virpipe/command/run_docker.py
VirPipe-1.0.11.dist-info/METADATA
VirPipe-1.0.11.dist-info/WHEEL
VirPipe-1.0.11.dist-info/entry_points.txt
VirPipe-1.0.11.dist-info/top_level.txt
VirPipe-1.0.11.dist-info/RECORD
